_shapelysmooth.pypy310-pp73-darwin.so
shapelysmooth-0.2.1.dist-info/RECORD
shapelysmooth-0.2.1.dist-info/WHEEL
shapelysmooth-0.2.1.dist-info/top_level.txt
shapelysmooth-0.2.1.dist-info/LICENSE.txt
shapelysmooth-0.2.1.dist-info/METADATA
shapelysmooth/__init__.py
shapelysmooth/py.typed
